    <item id="2641" name="enforced knight boots">
    <item id="6433" article="a" name="enforced paladin shield">
    <item id="7892" name="Enforced boots">
    <item id="7896" name="Enforced legs">
    <item id="7897" article="a" name="Enforced armor">
    <item id="7902" article="a" name="Enforced helmet">
    <item id="8880" article="a" name="enforced paladin armor">
    <item id="8926" article="a" name="Enforced Axe">
    <item id="8929" article="the" name="Enforced Club">
    <item id="2196" article="a" name="enforced amulet">
	<item id="2469" name="enforced paladin legs">
    <item id="2502" article="a" name="enforced knight helmet">
    <item id="2503" article="a" name="enforced knight armor">
    <item id="2504" name="enforced knight legs">
    <item id="2506" article="a" name="enforced paladin helmet">
    <item id="2537" article="an" name="enforced mage shield">


    <item id="7903" article="a" name="super helmet">
    <item id="7390" article="the" name="Super Sword">
    <item id="7884" article="a" name="Super Armor">
    <item id="7885" name="Super legs">
    <item id="7886" name="Super boots">
    <item id="7958" article="a" name="Super Wand">

    <item id="2184" article="a" name="Super rod">
    <item id="2272" article="a" name="Super UH">

	<item id="10134" article="a" name="infinity amulet of loss">
    
    <item id="12288" article="a" name="Pheonixia Wand">
    <item id="10310" article="a" name="pheonixia ring">
    <item id="11362" name="pheonixia Helmet">
    <item id="12288" article="a" name="Pheonixia Wand">

    <item id="12605" article="a" name="fortified shield">

	<item id="12610" article="a" name="sword of fury">
	<item id="12606" article="a" name="fury helmet">
    <item id="12574" article="a" name="axe of fury">
	<item id="12604" article="a" name="fury legs">
	<item id="12609" article="a" name="wand of fury">
	<item id="7735" article="the" name="fury repeater">
	<item id="7367" article="an" name="fury spear" plural="fury spears">
	<item id="7409" article="an" name="club of fury">
	<item id="12610" article="a" name="sword of fury">
    <item id="12606" article="a" name="fury helmet">
	<item id="12604" article="a" name="fury legs">

	<item id="12603" article="a" name="stronghold mail">
	<item id="12607" name="boots of strong haste">
	


